<?xml version="1.0" encoding="utf-8"?>
<Defs>
    <ThingDef ParentName="PlantBase">
        <defName>Plant_CelesCloth</defName>
        <label>待命名</label>
        <description>The gene editing products of Celestia are resistant to drought and flood, acid and alkali, and easy to survive, and will produce polymer fiber components with special structure that are easy to peel off in the phloem of the stem.</description>
        <statBases>
            <MaxHitPoints>185</MaxHitPoints>
            <Nutrition>0.2</Nutrition>
        </statBases>
        <!--<graphicData>
            <texPath>Things/Plant/CottonPlant</texPath>
            <graphicClass>Graphic_Random</graphicClass>
        </graphicData>-->
        <selectable>true</selectable>
        <pathCost>14</pathCost>
        <ingestible/>
        <plant>
            <growDays>12</growDays>
            <dieIfLeafless>true</dieIfLeafless>
            <harvestTag>Standard</harvestTag>
            <harvestedThingDef>CelesCloth</harvestedThingDef>
            <harvestYield>10</harvestYield>
            <sowTags>
                <li>Ground</li>
                <li>Hydroponic</li>
            </sowTags>
            <sowMinSkill>6</sowMinSkill>
            <topWindExposure>0.1</topWindExposure>
            <immatureGraphicPath>Things/Plant/CottonPlant_Immature</immatureGraphicPath>
            <visualSizeRange>0.3~1.05</visualSizeRange>
            <wildOrder>2</wildOrder>
        </plant>
    </ThingDef>
</Defs>