<?xml version="1.0" encoding="utf-8"?>
<Defs>

    <RecipeDef>
        <defName>Celes_Recipe_ForgeTerminal_Plasteel</defName>
        <label>make plasteel</label>
        <description>Make plasteel.</description>
        <jobString>Making plasteel.</jobString>
        <workSpeedStat>GeneralLaborSpeed</workSpeedStat>
        <workAmount>1800</workAmount>
        <formingTicks>60000</formingTicks><!-- 1 days -->
        <gestationCycles>2</gestationCycles>
        <soundWorking>Interact_Research</soundWorking>
        <recipeUsers>
            <li>Celes_ForgeTerminal</li>
        </recipeUsers>
        <ingredients>
            <li>
                <filter>
                    <thingDefs>
                        <li>Steel</li>
                    </thingDefs>
                </filter>
                <count>50</count>
            </li>
        </ingredients>
        <fixedIngredientFilter>
            <thingDefs>
                <li>Steel</li>
            </thingDefs>
        </fixedIngredientFilter>
        <products>
            <Plasteel>10</Plasteel>
        </products>
        <skillRequirements>
            <Crafting>2</Crafting>
            <Intellectual>1</Intellectual>
        </skillRequirements>
        <workSkill>Crafting</workSkill>
        <displayPriority>0</displayPriority>
    </RecipeDef>

</Defs>